{
  "lang":"fr",
  "name":"pipeline",
  "version":"0.0.0",
  "spacy_version":">=3.8.2,<3.9.0",
  "description":"",
  "author":"",
  "email":"",
  "url":"",
  "license":"",
  "spacy_git_version":"63f1b53",
  "vectors":{
    "width":0,
    "vectors":0,
    "keys":0,
    "name":null,
    "mode":"default"
  },
  "labels":{
    "tok2vec":[

    ],
    "morphologizer":[
      "Definite=Def|Gender=Fem|Number=Plur|POS=DET|PronType=Art",
      "Gender=Fem|Number=Plur|POS=NOUN",
      "Gender=Fem|Number=Plur|POS=ADJ",
      "Mood=Ind|Number=Plur|POS=AUX|Person=3|Tense=Pres|VerbForm=Fin",
      "Gender=Masc|Number=Sing|POS=VERB|Tense=Past|VerbForm=Part",
      "POS=ADV",
      "POS=ADP",
      "Gender=Masc|Number=Sing|POS=DET|PronType=Dem",
      "Gender=Masc|Number=Sing|POS=NOUN",
      "POS=SCONJ",
      "Gender=Masc|Number=Sing|POS=PRON|Person=3",
      "Number=Plur|POS=PRON|Person=3|PronType=Prs",
      "Mood=Ind|Number=Sing|POS=VERB|Person=3|Tense=Pres|VerbForm=Fin",
      "Definite=Def|Gender=Fem|Number=Sing|POS=DET|PronType=Art",
      "Gender=Fem|Number=Sing|POS=NOUN",
      "POS=PUNCT",
      "Mood=Ind|Number=Sing|POS=AUX|Person=3|Tense=Pres|VerbForm=Fin",
      "Gender=Fem|Number=Sing|POS=VERB|Tense=Past|VerbForm=Part",
      "Definite=Def|Gender=Masc|Number=Sing|POS=DET|PronType=Art",
      "POS=PROPN",
      "Gender=Masc|Number=Sing|POS=ADJ",
      "Gender=Fem|Number=Sing|POS=PRON|Person=3|PronType=Prs",
      "POS=ADV|Polarity=Neg",
      "Gender=Fem|Number=Sing|POS=ADJ",
      "POS=CCONJ",
      "Mood=Ind|Number=Plur|POS=VERB|Person=3|Tense=Pres|VerbForm=Fin",
      "Definite=Def|Gender=Masc|Number=Plur|POS=DET|PronType=Art",
      "Gender=Masc|Number=Plur|POS=NOUN",
      "Number=Sing|POS=PRON|Person=3|PronType=Dem",
      "POS=PRON|PronType=Rel",
      "Number=Sing|POS=PRON|Person=1|PronType=Prs",
      "Mood=Cnd|Number=Sing|POS=VERB|Person=1|Tense=Pres|VerbForm=Fin",
      "Gender=Masc|Number=Plur|POS=ADJ",
      "Gender=Masc|Number=Plur|POS=VERB|Tense=Past|VerbForm=Part",
      "Definite=Ind|Gender=Masc|Number=Sing|POS=DET|PronType=Art",
      "Gender=Fem|Number=Sing|POS=DET|Poss=Yes|PronType=Prs",
      "POS=VERB|Tense=Pres|VerbForm=Part",
      "Gender=Masc|Number=Sing|POS=PRON|Person=3|PronType=Prs",
      "Definite=Ind|Gender=Fem|Number=Plur|POS=DET|PronType=Art",
      "POS=VERB|VerbForm=Inf",
      "Gender=Masc|Number=Plur|POS=PRON|Person=3|PronType=Prs",
      "Mood=Ind|Number=Plur|POS=VERB|Person=3|Tense=Imp|VerbForm=Fin",
      "Gender=Fem|Number=Plur|POS=DET",
      "POS=AUX|Tense=Pres|VerbForm=Part",
      "Mood=Cnd|Number=Sing|POS=AUX|Person=3|Tense=Pres|VerbForm=Fin",
      "POS=PRON|Person=3|PronType=Prs",
      "Definite=Ind|Gender=Masc|Number=Plur|POS=DET|PronType=Art",
      "POS=PRON",
      "Mood=Ind|Number=Sing|POS=VERB|Person=3|Tense=Imp|VerbForm=Fin",
      "Definite=Def|Number=Plur|POS=DET|PronType=Art",
      "Number=Sing|POS=PRON|Person=3|PronType=Prs",
      "Definite=Ind|Gender=Fem|Number=Sing|POS=DET|PronType=Art",
      "Gender=Masc|Number=Plur|POS=DET|Poss=Yes|PronType=Prs",
      "POS=NUM",
      "Gender=Fem|Number=Sing|POS=PRON|PronType=Rel",
      "Mood=Ind|Number=Sing|POS=AUX|Person=3|Tense=Imp|VerbForm=Fin",
      "Gender=Masc|Number=Plur|POS=DET",
      "POS=SYM",
      "Definite=Def|Number=Sing|POS=DET|PronType=Art",
      "Gender=Masc|NumType=Ord|Number=Sing|POS=ADJ",
      "POS=X",
      "POS=PART",
      "Gender=Fem|Number=Sing|POS=PRON",
      "POS=AUX|VerbForm=Inf",
      "Gender=Masc|Number=Sing|POS=DET|Poss=Yes|PronType=Prs",
      "Number=Plur|POS=PRON|Person=2|PronType=Prs",
      "Mood=Ind|Number=Plur|POS=VERB|Person=2|Tense=Pres|VerbForm=Fin",
      "Mood=Sub|Number=Plur|POS=VERB|Person=3|Tense=Pres|VerbForm=Fin",
      "Gender=Masc|Number=Sing|POS=DET",
      "Number=Sing|POS=PRON",
      "Number=Plur|POS=PRON|Person=1|PronType=Prs",
      "Mood=Ind|Number=Plur|POS=AUX|Person=3|Tense=Imp|VerbForm=Fin",
      "Mood=Sub|Number=Sing|POS=VERB|Person=3|Tense=Pres|VerbForm=Fin",
      "Gender=Fem|Number=Sing|POS=DET|PronType=Dem",
      "Mood=Sub|Number=Sing|POS=AUX|Person=3|Tense=Pres|VerbForm=Fin",
      "Gender=Masc|Number=Sing|POS=AUX|Tense=Past|VerbForm=Part",
      "Mood=Ind|Number=Sing|POS=VERB|Person=3|Tense=Past|VerbForm=Fin",
      "Gender=Fem|Number=Plur|POS=VERB|Tense=Past|VerbForm=Part",
      "Gender=Fem|Number=Plur|POS=PRON|Person=3|PronType=Prs",
      "Mood=Cnd|Number=Sing|POS=VERB|Person=3|Tense=Pres|VerbForm=Fin",
      "Number=Plur|POS=PRON",
      "Gender=Fem|NumType=Ord|Number=Sing|POS=ADJ",
      "Mood=Ind|Number=Sing|POS=VERB|Person=3|Tense=Fut|VerbForm=Fin",
      "Gender=Fem|Number=Sing|POS=PRON|PronType=Dem",
      "Mood=Ind|Number=Sing|POS=AUX|Person=3|Tense=Fut|VerbForm=Fin",
      "Gender=Fem|Number=Plur|POS=DET|Poss=Yes|PronType=Prs",
      "Gender=Fem|Number=Sing|POS=DET",
      "POS=PRON|Person=3",
      "Mood=Ind|Number=Sing|POS=AUX|Person=3|Tense=Past|VerbForm=Fin",
      "Gender=Masc|Number=Plur|POS=PRON",
      "Mood=Ind|Number=Plur|POS=VERB|Person=3|Tense=Past|VerbForm=Fin",
      "Definite=Def|POS=DET",
      "Mood=Ind|Number=Plur|POS=AUX|Person=1|Tense=Pres|VerbForm=Fin",
      "Gender=Masc|Number=Sing|POS=DET|Polarity=Neg|PronType=Neg",
      "POS=NOUN",
      "Gender=Masc|Number=Sing|POS=PRON|Person=3|Reflex=Yes",
      "Gender=Masc|Number=Sing|POS=PRON|PronType=Dem",
      "Number=Sing|POS=DET",
      "Number=Sing|POS=PRON|PronType=Dem",
      "Gender=Masc|Number=Plur|POS=PRON|PronType=Dem",
      "Mood=Ind|Number=Sing|POS=VERB|Person=1|Tense=Pres|VerbForm=Fin",
      "Mood=Ind|Number=Plur|POS=AUX|Person=3|Tense=Past|VerbForm=Fin",
      "Gender=Masc|Number=Plur|POS=DET|PronType=Dem",
      "Gender=Masc|Number=Sing|POS=PRON|PronType=Rel",
      "Gender=Fem|Number=Plur|POS=PRON|PronType=Dem",
      "POS=ADJ",
      "Gender=Masc|Number=Sing|POS=PRON",
      "Gender=Fem|Number=Plur|POS=PRON",
      "Number=Plur|POS=DET|PronType=Dem",
      "Number=Plur|POS=NOUN",
      "Mood=Imp|Number=Plur|POS=VERB|Person=1|Tense=Pres|VerbForm=Fin",
      "Definite=Ind|POS=DET|PronType=Art",
      "Gender=Masc|Number=Plur|POS=PRON|Person=3",
      "Gender=Fem|Number=Plur|POS=DET|PronType=Dem",
      "Mood=Ind|Number=Plur|POS=VERB|Person=1|Tense=Pres|VerbForm=Fin",
      "Number=Sing|POS=PRON|Person=3",
      "Mood=Ind|Number=Plur|POS=VERB|Person=3|Tense=Fut|VerbForm=Fin",
      "Mood=Ind|Number=Plur|POS=AUX|Person=3|Tense=Fut|VerbForm=Fin",
      "Gender=Masc|Number=Sing|POS=PRON|Person=3|PronType=Dem",
      "Mood=Cnd|Number=Plur|POS=VERB|Person=3|Tense=Pres|VerbForm=Fin",
      "Mood=Cnd|Number=Plur|POS=VERB|Person=1|Tense=Pres|VerbForm=Fin",
      "Number=Sing|POS=NOUN",
      "Mood=Ind|Number=Sing|POS=AUX|Person=1|Tense=Pres|VerbForm=Fin",
      "Mood=Imp|Number=Plur|POS=VERB|Person=2|Tense=Pres|VerbForm=Fin",
      "Mood=Ind|Number=Plur|POS=AUX|Person=1|Tense=Imp|VerbForm=Fin",
      "Number=Sing|POS=DET|Poss=Yes|PronType=Prs",
      "Number=Plur|POS=DET",
      "Mood=Sub|Number=Plur|POS=AUX|Person=3|Tense=Pres|VerbForm=Fin",
      "Gender=Fem|Number=Sing|POS=DET|Polarity=Neg|PronType=Neg",
      "Definite=Def|Gender=Masc|Number=Sing|POS=DET",
      "Number=Plur|POS=DET|Poss=Yes|PronType=Prs",
      "Definite=Def|Gender=Fem|Number=Plur|POS=DET",
      "POS=VERB",
      "POS=INTJ",
      "Number=Sing|POS=PRON|Polarity=Neg",
      "Mood=Cnd|Number=Plur|POS=AUX|Person=3|Tense=Pres|VerbForm=Fin",
      "Gender=Masc|Number=Sing|POS=DET|PronType=Prs",
      "Mood=Ind|Number=Sing|POS=VERB|Person=1|Tense=Imp|VerbForm=Fin",
      "Mood=Ind|Number=Sing|POS=AUX|Person=1|Tense=Imp|VerbForm=Fin",
      "Mood=Ind|Number=Sing|POS=VERB|Person=1|Tense=Fut|VerbForm=Fin",
      "POS=DET|Poss=Yes",
      "Gender=Fem|Number=Sing|POS=DET|PronType=Prs",
      "Number=Sing|POS=PRON|Person=1",
      "Gender=Fem|Number=Sing|POS=PRON|Person=3|Reflex=Yes",
      "Gender=Masc|Number=Plur|POS=PRON|PronType=Rel",
      "Mood=Ind|Number=Plur|POS=VERB|Person=2|Tense=Fut|VerbForm=Fin",
      "Gender=Fem|Number=Plur|POS=PRON|PronType=Rel",
      "Mood=Ind|Number=Plur|POS=VERB|Person=1|Tense=Fut|VerbForm=Fin",
      "POS=PRON|PronType=Ind",
      "Mood=Ind|Number=Plur|POS=AUX|Person=1|Tense=Fut|VerbForm=Fin",
      "Definite=Ind|Number=Plur|POS=DET|PronType=Art",
      "Gender=Masc|Number=Plur|POS=PRON|PronType=Prs",
      "Number=Sing|POS=DET|PronType=Dem",
      "Gender=Masc|Number=Plur|POS=PRON|Person=3|Reflex=Yes",
      "POS=NOUN|Poss=Yes",
      "POS=PROPN|Poss=Yes",
      "Mood=Sub|Number=Sing|POS=AUX|Person=3|Tense=Imp|VerbForm=Fin",
      "Mood=Cnd|Number=Plur|POS=AUX|Person=2|Tense=Pres|VerbForm=Fin",
      "Mood=Cnd|Number=Plur|POS=AUX|Person=1|Tense=Pres|VerbForm=Fin",
      "Number=Plur|POS=PRON|PronType=Prs",
      "Mood=Ind|Number=Plur|POS=AUX|Person=2|Tense=Fut|VerbForm=Fin",
      "POS=PRON|PronType=Dem",
      "Mood=Ind|Number=Sing|POS=VERB|Person=2|Tense=Pres|VerbForm=Fin",
      "POS=PRON|PronType=Prs",
      "NumType=Ord|POS=ADJ",
      "Mood=Sub|Number=Sing|POS=VERB|Person=3|Tense=Imp|VerbForm=Fin",
      "Gender=Fem|Number=Plur|POS=PRON|Person=3|Reflex=Yes",
      "POS=DET|Polarity=Neg",
      "Mood=Ind|Number=Plur|POS=AUX|Person=2|Tense=Pres|VerbForm=Fin",
      "Number=Sing|POS=PRON|Person=2|PronType=Prs",
      "POS=AUX",
      "Mood=Cnd|Number=Sing|POS=AUX|Person=1|Tense=Pres|VerbForm=Fin",
      "Number=Sing|POS=PRON|PronType=Neg",
      "Case=Voc|Gender=Masc|Number=Sing|POS=NOUN",
      "Mood=Imp|Number=Sing|POS=VERB|Person=2|Tense=Pres|VerbForm=Fin",
      "Gender=Masc|Number=Sing|POS=PRON|Person=2",
      "Mood=Sub|Number=Plur|POS=VERB|Person=1|Tense=Pres|VerbForm=Fin",
      "POS=PRON|Polarity=Neg",
      "Number=Sing|POS=PRON|Person=1|Reflex=Yes",
      "Gender=Fem|Number=Sing|POS=DET|PronType=Neg",
      "Number=Sing|POS=ADJ",
      "Mood=Sub|Number=Plur|POS=VERB|Person=2|Tense=Pres|VerbForm=Fin",
      "Number=Sing|POS=PRON|Person=2",
      "Mood=Ind|Number=Plur|POS=VERB|Person=1|Tense=Imp|VerbForm=Fin",
      "Mood=Sub|Number=Sing|POS=VERB|Person=1|Tense=Pres|VerbForm=Fin",
      "Definite=Def|Gender=Masc|Number=Plur|POS=DET",
      "POS=DET",
      "Definite=Ind|Gender=Fem|Number=Plur|POS=DET",
      "Mood=Cnd|Number=Plur|POS=VERB|Person=2|Tense=Pres|VerbForm=Fin",
      "Gender=Fem|Number=Sing|POS=PRON|Person=1|Reflex=Yes",
      "Definite=Def|Number=Sing|POS=DET",
      "Gender=Masc|Number=Sing|POS=NOUN|PronType=Art",
      "Mood=Ind|Number=Sing|POS=AUX|Person=2|Tense=Pres|VerbForm=Fin",
      "Gender=Masc|Number=Sing|POS=PROPN",
      "Gender=Masc|Number=Sing|POS=DET|Polarity=Neg",
      "Mood=Sub|Number=Sing|POS=AUX|Person=1|Tense=Pres|VerbForm=Fin",
      "Mood=Sub|Number=Sing|POS=VERB|Person=2|Tense=Pres|VerbForm=Fin",
      "Gender=Masc|Number=Plur|POS=NOUN|Tense=Past",
      "Degree=Cmp|POS=ADJ",
      "Gender=Masc|Number=Sing|POS=PRON|Person=3|PronType=Rel",
      "Gender=Fem|POS=NOUN",
      "POS=PART|Polarity=Neg",
      "Gender=Fem|Number=Sing|POS=AUX|Tense=Past|VerbForm=Part",
      "Gender=Fem|Number=Sing|POS=NOUN|Tense=Past",
      "Mood=Sub|Number=Plur|POS=AUX|Person=2|Tense=Pres|VerbForm=Fin",
      "Mood=Ind|Number=Plur|POS=VERB|Person=1|Tense=Past|VerbForm=Fin",
      "Number=Plur|POS=PRON|Person=3|PronType=Rel",
      "Gender=Masc|Number=Sing|POS=PRON|PronType=Prs",
      "Gender=Neut|Number=Sing|POS=ADJ",
      "Gender=Neut|Number=Sing|POS=NOUN",
      "Number=Sing|POS=PRON|PronType=Prs",
      "Gender=Masc|Number=Sing|POS=PRON|Person=1|Reflex=Yes",
      "Case=Abl|Gender=Fem|Number=Sing|POS=NOUN",
      "Mood=Imp|Number=Plur|POS=AUX|Person=2|Tense=Pres|VerbForm=Fin",
      "Definite=Def|Gender=Fem|Number=Sing|POS=DET",
      "Gender=Fem|Number=Sing|POS=NOUN|PronType=Art",
      "Gender=Fem|Number=Plur|POS=PRON|Person=3|PronType=Rel",
      "Definite=Def|POS=DET|PronType=Art",
      "Number=Sing|POS=PRON|Person=3|PronType=Int",
      "Gender=Fem|Number=Plur|POS=NUM",
      "Gender=Fem|Number=Sing|POS=PROPN",
      "Mood=Ind|Number=Sing|POS=VERB|Person=1|Tense=Past|VerbForm=Fin",
      "POS=DET|PronType=Prs",
      "POS=PRON|Poss=Yes",
      "Gender=Fem|Number=Plur|POS=DET|PronType=Neg",
      "Mood=Ind|Number=Sing|POS=VERB|Person=2|Tense=Imp|VerbForm=Fin",
      "POS=PRON|Person=2|PronType=Prs"
    ],
    "parser":[
      "ROOT",
      "acl",
      "acl:relcl",
      "advcl",
      "advmod",
      "amod",
      "appos",
      "aux",
      "aux:caus",
      "aux:pass",
      "case",
      "cc",
      "ccomp",
      "compound",
      "conj",
      "cop",
      "dep",
      "det",
      "expl",
      "fixed",
      "flat:name",
      "iobj",
      "mark",
      "nmod",
      "nsubj",
      "nsubj:caus",
      "nsubj:pass",
      "nummod",
      "obj",
      "obj:agent",
      "obl",
      "parataxis",
      "punct",
      "xcomp"
    ]
  },
  "pipeline":[
    "tok2vec",
    "morphologizer",
    "parser"
  ],
  "components":[
    "tok2vec",
    "morphologizer",
    "parser"
  ],
  "disabled":[

  ],
  "performance":{
    "pos_acc":0.870599073,
    "morph_acc":0.8256888659,
    "morph_per_feat":{
      "Definite":{
        "p":0.9701338826,
        "r":0.7721311475,
        "f":0.8598813327
      },
      "Gender":{
        "p":0.8291051978,
        "r":0.7580360519,
        "f":0.7919794548
      },
      "Number":{
        "p":0.9588070718,
        "r":0.8657350175,
        "f":0.9098971868
      },
      "PronType":{
        "p":0.971682992,
        "r":0.8023529412,
        "f":0.87893677
      },
      "Mood":{
        "p":0.9142857143,
        "r":0.8178913738,
        "f":0.8634064081
      },
      "Person":{
        "p":0.9320288363,
        "r":0.8297677262,
        "f":0.877930477
      },
      "Tense":{
        "p":0.8044268252,
        "r":0.7202011239,
        "f":0.7599875156
      },
      "VerbForm":{
        "p":0.8625605931,
        "r":0.7744495648,
        "f":0.816133819
      },
      "Poss":{
        "p":0.9352112676,
        "r":0.9299719888,
        "f":0.9325842697
      },
      "Polarity":{
        "p":0.9907407407,
        "r":0.9224137931,
        "f":0.9553571429
      },
      "NumType":{
        "p":0.0,
        "r":0.0,
        "f":0.0
      },
      "Reflex":{
        "p":0.0,
        "r":0.0,
        "f":0.0
      },
      "Case":{
        "p":0.0,
        "r":0.0,
        "f":0.0
      }
    },
    "dep_uas":0.7186052414,
    "dep_las":0.6372679465,
    "dep_las_per_type":{
      "root":{
        "p":0.6342182891,
        "r":0.7273342355,
        "f":0.6775921841
      },
      "det":{
        "p":0.9004921892,
        "r":0.7610779526,
        "f":0.824936287
      },
      "appos":{
        "p":0.2726218097,
        "r":0.3846153846,
        "f":0.3190767142
      },
      "case":{
        "p":0.8450764007,
        "r":0.748777736,
        "f":0.7940179462
      },
      "nmod":{
        "p":0.5905125409,
        "r":0.7181697613,
        "f":0.6481149013
      },
      "nsubj":{
        "p":0.7018181818,
        "r":0.6252699784,
        "f":0.6613363792
      },
      "nummod":{
        "p":0.6312178388,
        "r":0.7117988395,
        "f":0.6690909091
      },
      "obj":{
        "p":0.5314599878,
        "r":0.6937799043,
        "f":0.6018678658
      },
      "cc":{
        "p":0.8210290828,
        "r":0.7734457323,
        "f":0.796527401
      },
      "conj":{
        "p":0.3902702703,
        "r":0.2956592957,
        "f":0.3364398882
      },
      "advmod":{
        "p":0.6038543897,
        "r":0.4938704028,
        "f":0.5433526012
      },
      "obl":{
        "p":0.5404294198,
        "r":0.4904643449,
        "f":0.5142360356
      },
      "amod":{
        "p":0.6385099685,
        "r":0.6469962786,
        "f":0.6427251122
      },
      "acl:relcl":{
        "p":0.4944444444,
        "r":0.2966666667,
        "f":0.3708333333
      },
      "cop":{
        "p":0.6803652968,
        "r":0.6711711712,
        "f":0.6757369615
      },
      "parataxis":{
        "p":0.5,
        "r":0.0204081633,
        "f":0.0392156863
      },
      "acl":{
        "p":0.2009345794,
        "r":0.0872210953,
        "f":0.1216407355
      },
      "compound":{
        "p":0.0,
        "r":0.0,
        "f":0.0
      },
      "flat:name":{
        "p":0.7216494845,
        "r":0.7313432836,
        "f":0.7264640474
      },
      "mark":{
        "p":0.6639784946,
        "r":0.4515539305,
        "f":0.5375408052
      },
      "advcl":{
        "p":0.1588235294,
        "r":0.1942446043,
        "f":0.1747572816
      },
      "aux":{
        "p":0.688372093,
        "r":0.7167070218,
        "f":0.7022538553
      },
      "fixed":{
        "p":0.5696969697,
        "r":0.2554347826,
        "f":0.3527204503
      },
      "nsubj:pass":{
        "p":0.4267782427,
        "r":0.4636363636,
        "f":0.4444444444
      },
      "xcomp":{
        "p":0.2919708029,
        "r":0.3680981595,
        "f":0.3256445047
      },
      "aux:pass":{
        "p":0.61328125,
        "r":0.646090535,
        "f":0.629258517
      },
      "ccomp":{
        "p":0.0,
        "r":0.0,
        "f":0.0
      },
      "iobj":{
        "p":0.0,
        "r":0.0,
        "f":0.0
      },
      "aux:caus":{
        "p":0.0,
        "r":0.0,
        "f":0.0
      },
      "goeswith":{
        "p":0.0,
        "r":0.0,
        "f":0.0
      },
      "nsubj:caus":{
        "p":0.0,
        "r":0.0,
        "f":0.0
      },
      "obj:agent":{
        "p":0.0,
        "r":0.0,
        "f":0.0
      },
      "dep":{
        "p":0.0,
        "r":0.0,
        "f":0.0
      },
      "dislocated":{
        "p":0.0,
        "r":0.0,
        "f":0.0
      },
      "expl":{
        "p":0.8,
        "r":0.037037037,
        "f":0.0707964602
      },
      "vocative":{
        "p":0.0,
        "r":0.0,
        "f":0.0
      },
      "reparandum":{
        "p":0.0,
        "r":0.0,
        "f":0.0
      },
      "csubj":{
        "p":0.0,
        "r":0.0,
        "f":0.0
      },
      "orphan":{
        "p":0.0,
        "r":0.0,
        "f":0.0
      },
      "discourse":{
        "p":0.0,
        "r":0.0,
        "f":0.0
      }
    },
    "sents_p":0.7267338471,
    "sents_r":0.8294993234,
    "sents_f":0.7747235387,
    "tok2vec_loss":4096.7788019702,
    "morphologizer_loss":19210.4978599548,
    "parser_loss":37619.38671875
  }
}